LICENSE.md
MANIFEST.in
README.md
setup.py
admin_datta/__init__.py
admin_datta/admin.py
admin_datta/apps.py
admin_datta/forms.py
admin_datta/urls.py
admin_datta/utils.py
admin_datta/views.py
admin_datta/static/assets/css/forms.css
admin_datta/static/assets/css/landing.css
admin_datta/static/assets/css/style-preset.css
admin_datta/static/assets/css/style.css
admin_datta/static/assets/css/widgets.css
admin_datta/static/assets/css/plugins/bootstrap.min.css
admin_datta/static/assets/css/plugins/jsvectormap.min.css
admin_datta/static/assets/fonts/feather.css
admin_datta/static/assets/fonts/fontawesome.css
admin_datta/static/assets/fonts/material.css
admin_datta/static/assets/fonts/tabler-icons.min.css
admin_datta/static/assets/fonts/feather/feather.eot
admin_datta/static/assets/fonts/feather/feather.svg
admin_datta/static/assets/fonts/feather/feather.ttf
admin_datta/static/assets/fonts/feather/feather.woff
admin_datta/static/assets/fonts/fontawesome/fa-brands-400.eot
admin_datta/static/assets/fonts/fontawesome/fa-brands-400.svg
admin_datta/static/assets/fonts/fontawesome/fa-brands-400.ttf
admin_datta/static/assets/fonts/fontawesome/fa-brands-400.woff
admin_datta/static/assets/fonts/fontawesome/fa-brands-400.woff2
admin_datta/static/assets/fonts/fontawesome/fa-regular-400.eot
admin_datta/static/assets/fonts/fontawesome/fa-regular-400.svg
admin_datta/static/assets/fonts/fontawesome/fa-regular-400.ttf
admin_datta/static/assets/fonts/fontawesome/fa-regular-400.woff
admin_datta/static/assets/fonts/fontawesome/fa-regular-400.woff2
admin_datta/static/assets/fonts/fontawesome/fa-solid-900.eot
admin_datta/static/assets/fonts/fontawesome/fa-solid-900.svg
admin_datta/static/assets/fonts/fontawesome/fa-solid-900.ttf
admin_datta/static/assets/fonts/fontawesome/fa-solid-900.woff
admin_datta/static/assets/fonts/fontawesome/fa-solid-900.woff2
admin_datta/static/assets/fonts/inter/Inter-italic.var.woff2
admin_datta/static/assets/fonts/inter/Inter-roman.var.woff2
django_admin_datta.egg-info/PKG-INFO
django_admin_datta.egg-info/SOURCES.txt
django_admin_datta.egg-info/dependency_links.txt
django_admin_datta.egg-info/not-zip-safe
django_admin_datta.egg-info/top_level.txt
